CHANGES.rst
CONTRIBUTORS.rst
DEVELOP.rst
LICENSE.GPL
LICENSE.rst
MANIFEST.in
README.rst
setup.cfg
setup.py
docs/index.rst
src/collective/__init__.py
src/collective.discussion.mentioning.egg-info/PKG-INFO
src/collective.discussion.mentioning.egg-info/SOURCES.txt
src/collective.discussion.mentioning.egg-info/dependency_links.txt
src/collective.discussion.mentioning.egg-info/entry_points.txt
src/collective.discussion.mentioning.egg-info/namespace_packages.txt
src/collective.discussion.mentioning.egg-info/not-zip-safe
src/collective.discussion.mentioning.egg-info/requires.txt
src/collective.discussion.mentioning.egg-info/top_level.txt
src/collective/discussion/__init__.py
src/collective/discussion/mentioning/__init__.py
src/collective/discussion/mentioning/comment.py
src/collective/discussion/mentioning/configure.zcml
src/collective/discussion/mentioning/events.zcml
src/collective/discussion/mentioning/interfaces.py
src/collective/discussion/mentioning/permissions.zcml
src/collective/discussion/mentioning/setuphandlers.py
src/collective/discussion/mentioning/testing.py
src/collective/discussion/mentioning/upgrades.py
src/collective/discussion/mentioning/upgrades.zcml
src/collective/discussion/mentioning/browser/__init__.py
src/collective/discussion/mentioning/browser/configure.zcml
src/collective/discussion/mentioning/browser/views.py
src/collective/discussion/mentioning/browser/overrides/.gitkeep
src/collective/discussion/mentioning/browser/overrides/plone.app.discussion.browser.comments.pt
src/collective/discussion/mentioning/browser/static/.gitkeep
src/collective/discussion/mentioning/browser/static/index.js
src/collective/discussion/mentioning/browser/static/dist/indexcompiled.js
src/collective/discussion/mentioning/browser/static/dist/indexcompiled.js.map
src/collective/discussion/mentioning/browser/static/dist/indexcompiled.min.js
src/collective/discussion/mentioning/browser/static/dist/indexcompiled.min.js.map
src/collective/discussion/mentioning/browser/static/dist/tribute.css
src/collective/discussion/mentioning/locales/README.rst
src/collective/discussion/mentioning/locales/__init__.py
src/collective/discussion/mentioning/locales/collective.discussion.mentioning.pot
src/collective/discussion/mentioning/locales/update.py
src/collective/discussion/mentioning/locales/update.sh
src/collective/discussion/mentioning/locales/en/LC_MESSAGES/collective.discussion.mentioning.po
