Metadata-Version: 2.1
Name: collective.discussion.mentioning
Version: 1.0b1
Summary: An add-on for Plone plone.app.discussion allow mentioning in comment text area
Home-page: https://pypi.python.org/pypi/collective.discussion.mentioning
Author: RedTurtle
Author-email: sviluppo@redturtle.it
License: GPL version 2
Keywords: Python Plone
Platform: UNKNOWN
Classifier: Development Status :: 4 - Beta
Classifier: Environment :: Web Environment
Classifier: Framework :: Plone
Classifier: Framework :: Plone :: 5.0
Classifier: Framework :: Plone :: 5.1
Classifier: Programming Language :: Python
Classifier: Programming Language :: Python :: 2.7
Classifier: Operating System :: OS Independent
Classifier: License :: OSI Approved :: GNU General Public License v2 (GPLv2)
Provides-Extra: test
